{
  "data": [
    {
      "damage": 20,
      "hp": 400
    },
    {
      "damage": 30,
      "hp": 800
    },
    {
      "damage": 40,
      "hp": 1200
    },
    {
      "damage": 50,
      "hp": 1600
    },
    {
      "damage": 60,
      "hp": 2000
    },
    {
      "damage": 70,
      "hp": 2400
    },
    {
      "damage": 80,
      "hp": 2800
    },
    {
      "damage": 90,
      "hp": 3200
    },
    {
      "damage": 100,
      "hp": 36000
    },
    {
      "damage": 110,
      "hp": 4000
    }
  ]
}
